vault_explorer/__init__.py
vault_explorer/explorer.py
vault_explorer-0.1.1.dist-info/METADATA
vault_explorer-0.1.1.dist-info/WHEEL
vault_explorer-0.1.1.dist-info/licenses/LICENCE
vault_explorer-0.1.1.dist-info/RECORD
