Metadata-Version: 2.3
Name: vault-explorer
Version: 0.1.1
Summary: A module to recursively retrieve values from HashiCorp Vault KV store and apply functions on them.
Project-URL: Homepage, https://github.com/asakalys/vault-explorer
Project-URL: Issues, https://github.com/asakalys/vault-explorer/issues
Author-email: Aurimas Šakalys <aurimas.sakalys@vinted.com>
License-File: LICENCE
Classifier: License :: OSI Approved :: MIT License
Classifier: Operating System :: OS Independent
Classifier: Programming Language :: Python :: 3
Requires-Python: >=3.8
Requires-Dist: flatten-json~=0.1.14
Requires-Dist: hvac~=2.2.0
